<?xml version="1.0" encoding="UTF-8"?>
<config xmlns="http://www.knime.org/2008/09/XMLConfig" xmlns:xsi="http://www.w3.org/2001/XMLSchema-instance" xsi:schemaLocation="http://www.knime.org/2008/09/XMLConfig http://www.knime.org/XMLConfig_2008_09.xsd" key="spec.xml">
<entry key="spec_name" type="xstring" value="/dgulacsy/DE2_Term_Project/raw/main/wdis_of_interest.xlsx [WDI]"/>
<entry key="number_columns" type="xint" value="3"/>
<config key="column_spec_0">
<entry key="column_name" type="xstring" value="wdi"/>
<config key="element_names">
<entry key="array-size" type="xint" value="0"/>
</config>
<config key="column_type">
<entry key="cell_class" type="xstring" value="org.knime.core.data.def.StringCell"/>
</config>
<config key="column_domain">
<config key="possible_values">
<entry key="array-size" type="xint" value="9"/>
<config key="0">
<entry key="datacell" type="xstring" value="org.knime.core.data.def.StringCell"/>
<config key="org.knime.core.data.def.StringCell">
<entry key="StringCell" type="xstring" value="Smoking prevalence, females (% of adults)"/>
</config>
</config>
<config key="1">
<entry key="datacell" type="xstring" value="org.knime.core.data.def.StringCell"/>
<config key="org.knime.core.data.def.StringCell">
<entry key="StringCell" type="xstring" value="Smoking prevalence, males (% of adults)"/>
</config>
</config>
<config key="2">
<entry key="datacell" type="xstring" value="org.knime.core.data.def.StringCell"/>
<config key="org.knime.core.data.def.StringCell">
<entry key="StringCell" type="xstring" value="Total alcohol consumption per capita, male (liters of pure alcohol, projected estimates, male 15+ years of age)"/>
</config>
</config>
<config key="3">
<entry key="datacell" type="xstring" value="org.knime.core.data.def.StringCell"/>
<config key="org.knime.core.data.def.StringCell">
<entry key="StringCell" type="xstring" value="Total alcohol consumption per capita, female (liters of pure alcohol, projected estimates, female 15+ years of age)"/>
</config>
</config>
<config key="4">
<entry key="datacell" type="xstring" value="org.knime.core.data.def.StringCell"/>
<config key="org.knime.core.data.def.StringCell">
<entry key="StringCell" type="xstring" value="Unemployment, female (% of female labor force) (modeled ILO estimate)"/>
</config>
</config>
<config key="5">
<entry key="datacell" type="xstring" value="org.knime.core.data.def.StringCell"/>
<config key="org.knime.core.data.def.StringCell">
<entry key="StringCell" type="xstring" value="Unemployment, male (% of male labor force) (modeled ILO estimate)"/>
</config>
</config>
<config key="6">
<entry key="datacell" type="xstring" value="org.knime.core.data.def.StringCell"/>
<config key="org.knime.core.data.def.StringCell">
<entry key="StringCell" type="xstring" value="Population"/>
</config>
</config>
<config key="7">
<entry key="datacell" type="xstring" value="org.knime.core.data.def.StringCell"/>
<config key="org.knime.core.data.def.StringCell">
<entry key="StringCell" type="xstring" value="Gini index (World Bank estimate)"/>
</config>
</config>
<config key="8">
<entry key="datacell" type="xstring" value="org.knime.core.data.def.StringCell"/>
<config key="org.knime.core.data.def.StringCell">
<entry key="StringCell" type="xstring" value="Government expenditure on education, total (% of GDP)"/>
</config>
</config>
</config>
</config>
<config key="column_properties"/>
<config key="meta_data"/>
</config>
<config key="column_spec_1">
<entry key="column_name" type="xstring" value="wdi_id"/>
<config key="element_names">
<entry key="array-size" type="xint" value="0"/>
</config>
<config key="column_type">
<entry key="cell_class" type="xstring" value="org.knime.core.data.def.StringCell"/>
</config>
<config key="column_domain">
<config key="possible_values">
<entry key="array-size" type="xint" value="9"/>
<config key="0">
<entry key="datacell" type="xstring" value="org.knime.core.data.def.StringCell"/>
<config key="org.knime.core.data.def.StringCell">
<entry key="StringCell" type="xstring" value="SH.PRV.SMOK.FE"/>
</config>
</config>
<config key="1">
<entry key="datacell" type="xstring" value="org.knime.core.data.def.StringCell"/>
<config key="org.knime.core.data.def.StringCell">
<entry key="StringCell" type="xstring" value="SH.PRV.SMOK.MA "/>
</config>
</config>
<config key="2">
<entry key="datacell" type="xstring" value="org.knime.core.data.def.StringCell"/>
<config key="org.knime.core.data.def.StringCell">
<entry key="StringCell" type="xstring" value="SH.ALC.PCAP.MA.LI"/>
</config>
</config>
<config key="3">
<entry key="datacell" type="xstring" value="org.knime.core.data.def.StringCell"/>
<config key="org.knime.core.data.def.StringCell">
<entry key="StringCell" type="xstring" value="SH.ALC.PCAP.FE.LI "/>
</config>
</config>
<config key="4">
<entry key="datacell" type="xstring" value="org.knime.core.data.def.StringCell"/>
<config key="org.knime.core.data.def.StringCell">
<entry key="StringCell" type="xstring" value="SL.UEM.TOTL.MA.ZS"/>
</config>
</config>
<config key="5">
<entry key="datacell" type="xstring" value="org.knime.core.data.def.StringCell"/>
<config key="org.knime.core.data.def.StringCell">
<entry key="StringCell" type="xstring" value="SL.UEM.TOTL.FE.ZS"/>
</config>
</config>
<config key="6">
<entry key="datacell" type="xstring" value="org.knime.core.data.def.StringCell"/>
<config key="org.knime.core.data.def.StringCell">
<entry key="StringCell" type="xstring" value="SP.POP.TOTL"/>
</config>
</config>
<config key="7">
<entry key="datacell" type="xstring" value="org.knime.core.data.def.StringCell"/>
<config key="org.knime.core.data.def.StringCell">
<entry key="StringCell" type="xstring" value="SI.POV.GINI"/>
</config>
</config>
<config key="8">
<entry key="datacell" type="xstring" value="org.knime.core.data.def.StringCell"/>
<config key="org.knime.core.data.def.StringCell">
<entry key="StringCell" type="xstring" value="SE.XPD.TOTL.GD.ZS"/>
</config>
</config>
</config>
</config>
<config key="column_properties"/>
<config key="meta_data"/>
</config>
<config key="column_spec_2">
<entry key="column_name" type="xstring" value="gender"/>
<config key="element_names">
<entry key="array-size" type="xint" value="0"/>
</config>
<config key="column_type">
<entry key="cell_class" type="xstring" value="org.knime.core.data.def.StringCell"/>
</config>
<config key="column_domain">
<config key="possible_values">
<entry key="array-size" type="xint" value="2"/>
<config key="0">
<entry key="datacell" type="xstring" value="org.knime.core.data.def.StringCell"/>
<config key="org.knime.core.data.def.StringCell">
<entry key="StringCell" type="xstring" value="f"/>
</config>
</config>
<config key="1">
<entry key="datacell" type="xstring" value="org.knime.core.data.def.StringCell"/>
<config key="org.knime.core.data.def.StringCell">
<entry key="StringCell" type="xstring" value="m"/>
</config>
</config>
</config>
</config>
<config key="column_properties"/>
<config key="meta_data"/>
</config>
</config>
